coloc/__init__.py
coloc/coloc.py
coloc-0.4.2.dist-info/LICENSE
coloc-0.4.2.dist-info/METADATA
coloc-0.4.2.dist-info/WHEEL
coloc-0.4.2.dist-info/top_level.txt
coloc-0.4.2.dist-info/RECORD
