Metadata-Version: 2.1
Name: coloc
Version: 0.4.2
Summary: the COLOC method by Giambartolomei et al.
Home-page: https://gitlab.com/aaylward/coloc
Author: Anthony Aylward
Author-email: aaylward@salk.edu
License: UNKNOWN
Platform: UNKNOWN
Classifier: Programming Language :: Python :: 3
Classifier: License :: OSI Approved :: MIT License
Classifier: Operating System :: OS Independent
License-File: LICENSE
Requires-Dist: pandas
Requires-Dist: sumstats
